manga_stitcher/__init__.py
manga_stitcher/__main__.py
manga_stitcher/cli.py
manga_stitcher/manga_stitcher.py
manga_stitcher-1.0.0.dist-info/licenses/LICENSE
manga_stitcher-1.0.0.dist-info/METADATA
manga_stitcher-1.0.0.dist-info/WHEEL
manga_stitcher-1.0.0.dist-info/entry_points.txt
manga_stitcher-1.0.0.dist-info/top_level.txt
manga_stitcher-1.0.0.dist-info/RECORD
