Metadata-Version: 2.4
Name: manga_stitcher
Version: 1.0.0
Summary: A straightforward tool designed to automatically combine manga pages vertically, creating a seamless reading experience
Author-email: recoskyler <38231748+recoskyler@users.noreply.github.com>
License-Expression: MIT
Project-URL: Homepage, https://github.com/recoskyler/manga-stitcher
Project-URL: Issues, https://github.com/recoskyler/manga-stitcher/issues
Classifier: Programming Language :: Python :: 3
Classifier: Operating System :: OS Independent
Requires-Python: >=3.10
License-File: LICENSE
Dynamic: license-file
